<?xml version="1.0" encoding="utf-8"?>
<monster name="Barkless Devotee" nameDescription="a barkless devotee" race="blood" experience="2200" speed="300" manacost="0">
	<health now="2800" max="2800" />
	<look type="990" head="0" body="0" legs="0" feet="0" addons="2" mount="0" corpse="0" />
	<targetchange interval="2000" chance="0" />
	<flags>
		<flag attackable="1" />
		<flag hostile="1" />
		<flag summonable="0" />
		<flag convinceable="0" />
		<flag illusionable="0" />
		<flag isboss="0" />
		<flag ignorespawnblock="0" />
		<flag pushable="0" />
		<flag canpushitems="1" />
		<flag canpushcreatures="1" />
		<flag staticattack="90" />
		<flag targetdistance="1" />
		<flag healthhidden="0" />
		<flag canwalkonenergy="0" />
		<flag canwalkonfire="0" />
		<flag canwalkonpoison="1" />
	</flags>
	<immunities>
		<immunity paralyze="1" />
		<immunity outfit="0" />
		<immunity invisible="1" />
		<immunity drunk="1" />
		<immunity bleed="0" />
	</immunities>
	<elements>
		<element physicalPercent="0" />
		<element energyPercent="17" />
		<element earthPercent="0" />
		<element firePercent="10" />
		<element lifedrainPercent="0" />
		<element manadrainPercent="0" />
		<element drownPercent="0" />
		<element icePercent="15" />
		<element holyPercent="0" />
		<element deathPercent="15" />
	</elements>
	<attacks>
		<attack name="melee" interval="2000" chance="100" min="0" max="-200" />
	</attacks>
	<defenses armor="30" defense="30" />
	<loot>
		<item id="2148" name="gold coin" chance="49785" countmax="100" />
		<item id="28398" name="fig leaf" chance="4845" />
		<item id="28399" name="bed of nails" chance="981" />
		<item id="28400" name="torn shirt" chance="971" />
	</loot>
</monster>