<?xml version="1.0" encoding="UTF-8"?>
<monster name="Celebrating Orger" nameDescription="a celebrating orger" race="blood" experience="0" speed="230">
	<health now="700" max="700" />
	<look type="1255" head="79" body="6" legs="94" feet="2" addons="1" mount="0" corpse="0" />
	<targetchange interval="2000" chance="5" />
	<flags>
		<flag attackable="1" />
		<flag hostile="0" />
		<flag summonable="0" />
		<flag convinceable="0" />
		<flag illusionable="0" />
		<flag isboss="0" />
		<flag ignorespawnblock="0" />
		<flag pushable="1" />
		<flag canpushitems="1" />
		<flag canpushcreatures="0" />
		<flag staticattack="90" />
		<flag targetdistance="1" />
		<flag canwalkonenergy="1" />
		<flag canwalkonfire="1" />
		<flag canwalkonpoison="1" />
	</flags>
	<defenses armor="10" defense="5" />
	<immunities>
		<immunity drunk="1" />
		<immunity invisible="1" />
		<immunity paralyze="1" />
		<immunity physical="1" />
		<immunity energy="1" />
		<immunity earth="1" />
		<immunity fire="1" />
		<immunity lifedrain="1" />
		<immunity manadrain="1" />
		<immunity drown="1" />
		<immunity ice="1" />
		<immunity holy="1" />
		<immunity death="1" />
	</immunities>
	<voices interval="5000" chance="10">
		<voice sentence="Let's paaarty!!" />
		<voice sentence="More beeeer!" />
		<voice sentence="Paaaartimeee!" />
	</voices>
</monster>
