<?xml version="1.0" encoding="utf-8"?>
<monster name="Goshnar's Megalomania" nameDescription="Goshnar's Megalomania" race="blood" experience="0" speed="0" manacost="0">
	<health now="0" max="0" />
	<look type="0" head="0" body="0" legs="0" feet="0" addons="0" mount="0" corpse="0" />
	<targetchange interval="2000" chance="0" />
	<flags>
		<flag attackable="1" />
		<flag hostile="1" />
		<flag summonable="0" />
		<flag convinceable="0" />
		<flag illusionable="0" />
		<flag isboss="1" />
		<flag ignorespawnblock="0" />
		<flag pushable="0" />
		<flag canpushitems="0" />
		<flag canpushcreatures="0" />
		<flag staticattack="90" />
		<flag targetdistance="1" />
		<flag healthhidden="0" />
		<flag canwalkonenergy="1" />
		<flag canwalkonfire="1" />
		<flag canwalkonpoison="1" />
	</flags>
	<immunities>
		<immunity paralyze="1" />
		<immunity outfit="0" />
		<immunity invisible="1" />
		<immunity drunk="1" />
		<immunity bleed="0" />
	</immunities>
	<elements>
		<element physicalPercent="0" />
		<element energyPercent="0" />
		<element earthPercent="0" />
		<element firePercent="0" />
		<element lifedrainPercent="0" />
		<element manadrainPercent="0" />
		<element drownPercent="0" />
		<element icePercent="0" />
		<element holyPercent="0" />
		<element deathPercent="0" />
	</elements>
	<attacks>
		<attack name="melee" interval="2000" chance="100" min="0" max="-117" />
	</attacks>
	<defenses armor="10" defense="5" />
	<loot>
		<item id="2160" name="crystal coin" chance="100000" countmax="53" />
		<item id="2154" name="yellow gem" chance="100000" />
		<item id="26031" name="supreme health potion" chance="100000" countmax="244" />
		<item id="32717" name="giant sapphire" chance="50000" countmax="4" />
		<item id="2158" name="blue gem" chance="50000" countmax="7" />
		<item id="32716" name="giant emerald" chance="50000" countmax="7" />
		<item id="2153" name="violet gem" chance="50000" countmax="3" />
		<item id="26030" name="ultimate spirit potion" chance="50000" countmax="32" />
		<item id="2156" name="red gem" chance="20000" />
		<item id="35278" name="giant amethyst" chance="20000" />
		<item id="36581" name="megalomania's skull" chance="20000" />
		<item id="36584" name="megalomania's essence" chance="20000" />
		<item id="36609" name="figurine of megalomania" chance="20000" />
		<item id="36675" name="figurine of cruelty" chance="20000" />
		<item id="36677" name="figurine of greed" chance="20000" />
		<item id="36674" name="figurine of malice" chance="20000" />
		<item id="26029" name="ultimate mana potion" chance="20000" />
		<item id="36608" name="figurine of spite" chance="20000" />
		<item id="32715" name="giant ruby" chance="20000" />
		<item id="7443" name="bullseye potion" chance="20000" />
		<item id="2155" name="green gem" chance="20000" />
		<item id="7439" name="berserk potion" chance="20000" />
		<item name="giant shimmering pearl" chance="20000" />
		<item id="35279" name="giant topaz" chance="20000" />
		<item id="9971" name="gold ingot" chance="20000" />
		<item id="7440" name="mastermind potion" chance="20000" />
		<item id="36676" name="figurine of hatred" chance="20000" />
		<item id="36765" name="bag you desire" chance="20000" />
	</loot>
</monster>