<?xml version="1.0" encoding="UTF-8"?>
<monster name="Grand Commander Soeren" nameDescription="" experience="12" speed="0">
	<health now="17" max="17" />
	<look type="0" head="0" body="0" legs="0" feet="0" addons="0" corpse="0" />
	<targetchange interval="2000" chance="5" />
	<flags>
		<flag isboss="1" />
		<flag pushable="0" />
		<flag canpushitems="1" />
		<flag canpushcreatures="1" />
		<flag staticattack="90" />
		<flag targetdistance="1" />
		<flag canwalkonenergy="1" />
		<flag canwalkonfire="1" />
		<flag canwalkonpoison="1" />
	</flags>
	<immunities>
		<immunity paralyze="1" />
		<immunity invisible="1" />
		<immunity drunk="1" />
	</immunities>
	<elements>
		<element physicalPercent="50" />
		<element energyPercent="50" />
		<element earthPercent="50" />
		<element firePercent="50" />
		<element icePercent="50" />
		<element holyPercent="-25" />
		<element deathPercent="50" />
	</elements>
	<defenses armor="30" defense="30" />
	<loot>
		<item id="7762" name="small enchanted amethyst" chance="100000" />
		<item id="31477" name="patch of fine cloth" chance="1134" />
	</loot>
</monster>
