<?xml version="1.0" encoding="UTF-8"?>
<monster name="Rift Lord" nameDescription="a rift lord" race="fire" experience="0" speed="200" manacost="0">
	<health now="5" max="5" />
	<look type="12" head="9" body="19" legs="9" feet="85" corpse="0" />
	<flags>
		<flag summonable="0" />
		<flag attackable="0" />
		<flag hostile="0" />
		<flag illusionable="0" />
		<flag convinceable="0" />
		<flag pushable="0" />
		<flag canpushitems="1" />
		<flag canpushcreatures="0" />
		<flag staticattack="98" />
		<flag targetdistance="1" />
		<flag runonhealth="0" />
	</flags>
</monster>
